MANIFEST.in
README.md
pyproject.toml
setup.cfg
setup.py
docs/CODE_OF_CONDUCT.md
docs/CONTRIBUTING.md
docs/Makefile
docs/README.md
docs/conf.py
docs/index.rst
docs/explanations/a_walk_around_the_settings.rst
docs/explanations/main.rst
docs/explanations/microservice_base_class.rst
docs/explanations/microservice_cookiecutter_template.rst
docs/explanations/microservice_lifecycle.rst
docs/how_to_guides/install_tamarco.rst
docs/how_to_guides/main.rst
docs/how_to_guides/make_the_docs.rst
docs/how_to_guides/setup_a_logging_backend.rst
docs/how_to_guides/setup_a_metrics_backend.rst
docs/how_to_guides/setup_a_setting_backend.rst
docs/how_to_guides/setup_settings_for_a_resource.rst
docs/how_to_guides/setup_settings_for_a_specific_microservice.rst
docs/how_to_guides/use_logging_resource.rst
docs/how_to_guides/use_metrics_resource.rst
docs/reference/main.rst
docs/tutorials/main.rst
docs/tutorials/quick_start.rst
docs/tutorials/write_your_first_microservice.rst
examples/http_resource/microservice.py
examples/metrics_resource/microservice.py
examples/metrics_resource/prometheus_example.py
examples/settings_watcher/microservice.py
examples/status_resource/microservice.py
tamarco/__init__.py
tamarco/tamarco
tamarco.egg-info/PKG-INFO
tamarco.egg-info/SOURCES.txt
tamarco.egg-info/dependency_links.txt
tamarco.egg-info/not-zip-safe
tamarco.egg-info/requires.txt
tamarco.egg-info/top_level.txt
tamarco/codecs/__init__.py
tamarco/codecs/interface.py
tamarco/codecs/json.py
tamarco/codecs/pickle.py
tamarco/codecs/yaml.py
tamarco/core/__init__.py
tamarco/core/dependency_resolver.py
tamarco/core/microservice.py
tamarco/core/signals.py
tamarco/core/tasks.py
tamarco/core/utils.py
tamarco/core/logging/__init__.py
tamarco/core/logging/logging.py
tamarco/core/logging/formatters/__init__.py
tamarco/core/logging/formatters/colored.py
tamarco/core/logging/formatters/logstash.py
tamarco/core/logging/formatters/syslog.py
tamarco/core/logging/handlers/__init__.py
tamarco/core/logging/handlers/asyncronous.py
tamarco/core/logging/handlers/elasticsearch.py
tamarco/core/logging/handlers/http.py
tamarco/core/logging/handlers/logstash.py
tamarco/core/logging/handlers/redis.py
