Metadata-Version: 2.1
Name: tamarco
Version: 0.1.1
Summary: Microservices framework designed for asyncio and Python
Home-page: https://github.com/System73/tamarco
Author: System73 Engineering Team
Author-email: opensource@system73.com
License: UNKNOWN
Keywords: tamarco
Platform: UNKNOWN
Classifier: Development Status :: 4 - Beta
Classifier: License :: OSI Approved :: MIT License
Classifier: Intended Audience :: Developers
Classifier: Natural Language :: English
Classifier: Programming Language :: Python :: 3.6
Provides-Extra: ci
Provides-Extra: visibility
